{
  "modulos": [
    {
      "id": 1,
      "imagen": "https://i.ibb.co/dJ6cLF7X/front.png",
      "nombre": "Frontend Básico",
      "descripcion": "Aprende los fundamentos del desarrollo web.",
      "course_ids": [1, 2]
    },
    {
      "id": 2,
      "imagen": "https://i.ibb.co/Q30GdK2G/datasc.jpg",
      "nombre": "Backend Inicial",
      "descripcion": "Introducción al desarrollo del lado del servidor.",
      "course_ids": [3]
    }
  ],
  "cursos": [
    {
      "id": 1,
      "nombre": "HTML y CSS",
      "imagen": "https://i.ibb.co/SDD4ZybD/html.png",
      "descripcion": "Curso completo de HTML y CSS desde cero."
    },
    {
      "id": 2,
      "nombre": "JavaScript Básico",
      "imagen": "https://i.ibb.co/SDD4ZybD/html.png",
      "descripcion": "Aprende lógica de programación con JavaScript."
    },
    {
      "id": 3,
      "nombre": "Node.js para principiantes",
      "imagen": "https://i.ibb.co/SDD4ZybD/html.png",
      "descripcion": "Primeros pasos con Node.js y Express."
    }
  ]
}
